[
    {
        "event_properties.name": "daily_journal",
        "events": 1181,
        "users": 1047
    },
    {
        "event_properties.name": "study_hub",
        "events": 715,
        "users": 644
    },
    {
        "event_properties.name": "personal_and_work_pkm",
        "events": 708,
        "users": 619
    },
    {
        "event_properties.name": "project_management",
        "events": 684,
        "users": 606
    },
    {
        "event_properties.name": "habit_tracker",
        "events": 652,
        "users": 592
    },
    {
        "event_properties.name": "crm_basic_approach",
        "events": 581,
        "users": 536
    },
    {
        "event_properties.name": "para_tasks_resources_meeting_notes_crm",
        "events": 565,
        "users": 487
    },
    {
        "event_properties.name": "community_space",
        "events": 529,
        "users": 487
    },
    {
        "event_properties.name": "zen_system",
        "events": 606,
        "users": 484
    },
    {
        "event_properties.name": "family_space",
        "events": 413,
        "users": 384
    },
    {
        "event_properties.name": "data_vault",
        "events": 416,
        "users": 384
    },
    {
        "event_properties.name": "team_space",
        "events": 420,
        "users": 382
    },
    {
        "event_properties.name": "para_lite",
        "events": 455,
        "users": 371
    },
    {
        "event_properties.name": "movie_database",
        "events": 387,
        "users": 350
    },
    {
        "event_properties.name": "zettelkasten_smart_notes",
        "events": 354,
        "users": 320
    },
    {
        "event_properties.name": "freelance_dashboard",
        "events": 347,
        "users": 306
    },
    {
        "event_properties.name": "paid_subscriptions_tracking",
        "events": 314,
        "users": 298
    },
    {
        "event_properties.name": "ultimate_student_os",
        "events": 338,
        "users": 297
    },
    {
        "event_properties.name": "unified_space",
        "events": 335,
        "users": 293
    },
    {
        "event_properties.name": "homepages",
        "events": 287,
        "users": 265
    },
    {
        "event_properties.name": "integrated_library",
        "events": 316,
        "users": 263
    },
    {
        "event_properties.name": "trip_planner",
        "events": 248,
        "users": 230
    },
    {
        "event_properties.name": "startup_planner",
        "events": 236,
        "users": 222
    },
    {
        "event_properties.name": "recipe_book_and_meal_planner",
        "events": 248,
        "users": 217
    },
    {
        "event_properties.name": "para_and_coder_setup",
        "events": 230,
        "users": 204
    },
    {
        "event_properties.name": "language_flashcards",
        "events": 217,
        "users": 198
    },
    {
        "event_properties.name": "space_for_digital_creators",
        "events": 169,
        "users": 164
    },
    {
        "event_properties.name": "routine_set_ticker",
        "events": 171,
        "users": 154
    },
    {
        "event_properties.name": "frm_friends_relationship_management",
        "events": 157,
        "users": 142
    },
    {
        "event_properties.name": "subscription_tracker",
        "events": 152,
        "users": 137
    },
    {
        "event_properties.name": "anytype_for_content_creators",
        "events": 151,
        "users": 133
    },
    {
        "event_properties.name": "customizable_dashboard",
        "events": 141,
        "users": 121
    },
    {
        "event_properties.name": "advanced_project_management",
        "events": 134,
        "users": 121
    },
    {
        "event_properties.name": "plant_database",
        "events": 110,
        "users": 107
    },
    {
        "event_properties.name": "meeting_notes_management",
        "events": 115,
        "users": 94
    },
    {
        "event_properties.name": "simple_tables",
        "events": 97,
        "users": 88
    },
    {
        "event_properties.name": "story_forge_project_manager",
        "events": 90,
        "users": 80
    },
    {
        "event_properties.name": "neighbors_space",
        "events": 73,
        "users": 68
    },
    {
        "event_properties.name": "Daily Journal",
        "events": 61,
        "users": 56
    },
    {
        "event_properties.name": "Personal and Work PKM",
        "events": 58,
        "users": 54
    },
    {
        "event_properties.name": "rpg_repository",
        "events": 54,
        "users": 47
    },
    {
        "event_properties.name": "podcast_database",
        "events": 43,
        "users": 38
    },
    {
        "event_properties.name": "PARA - Lite",
        "events": 41,
        "users": 36
    },
    {
        "event_properties.name": "animation_database",
        "events": 39,
        "users": 34
    },
    {
        "event_properties.name": "Habit Tracker",
        "events": 32,
        "users": 29
    },
    {
        "event_properties.name": "formula_1",
        "events": 30,
        "users": 27
    },
    {
        "event_properties.name": "Trip Planner",
        "events": 27,
        "users": 26
    },
    {
        "event_properties.name": "plant_tracker",
        "events": 33,
        "users": 25
    },
    {
        "event_properties.name": "Data Vault",
        "events": 28,
        "users": 24
    },
    {
        "event_properties.name": "Fully integrated Experience",
        "events": 30,
        "users": 23
    },
    {
        "event_properties.name": "Study Hub",
        "events": 25,
        "users": 22
    },
    {
        "event_properties.name": "Recipe Book and Meal Planner",
        "events": 21,
        "users": 21
    },
    {
        "event_properties.name": "Zettelkasten: Smart Notes",
        "events": 29,
        "users": 21
    },
    {
        "event_properties.name": "Movie Database",
        "events": 20,
        "users": 20
    },
    {
        "event_properties.name": "Zen System",
        "events": 23,
        "users": 20
    },
    {
        "event_properties.name": "crochet_dashboard",
        "events": 20,
        "users": 19
    },
    {
        "event_properties.name": "Project Management",
        "events": 26,
        "users": 19
    },
    {
        "event_properties.name": "coffee_tracker",
        "events": 18,
        "users": 18
    },
    {
        "event_properties.name": "Integrated Library",
        "events": 26,
        "users": 18
    },
    {
        "event_properties.name": "Homepages",
        "events": 19,
        "users": 18
    },
    {
        "event_properties.name": "Family Space",
        "events": 18,
        "users": 17
    },
    {
        "event_properties.name": "classical_music_database",
        "events": 19,
        "users": 17
    },
    {
        "event_properties.name": "Ultimate Student OS",
        "events": 15,
        "users": 14
    },
    {
        "event_properties.name": "Team Space",
        "events": 16,
        "users": 14
    },
    {
        "event_properties.name": "adventure_hub",
        "events": 15,
        "users": 13
    },
    {
        "event_properties.name": "Paid Subscriptions Tracking",
        "events": 14,
        "users": 13
    },
    {
        "event_properties.name": "FRM: Friends Relationship Management",
        "events": 15,
        "users": 13
    },
    {
        "event_properties.name": "Unified Space",
        "events": 12,
        "users": 12
    },
    {
        "event_properties.name": "Space for Digital Creators",
        "events": 12,
        "users": 12
    },
    {
        "event_properties.name": "items_lent_out_borrowed_tracker",
        "events": 14,
        "users": 12
    },
    {
        "event_properties.name": "Subscription Tracker",
        "events": 11,
        "users": 11
    },
    {
        "event_properties.name": "CRM: Basic Approach",
        "events": 12,
        "users": 11
    },
    {
        "event_properties.name": "Routine Set Ticker",
        "events": 12,
        "users": 11
    },
    {
        "event_properties.name": "Language Flashcards",
        "events": 11,
        "users": 10
    },
    {
        "event_properties.name": "Story Forge Project Manager",
        "events": 7,
        "users": 7
    },
    {
        "event_properties.name": "Startup Planner",
        "events": 7,
        "users": 7
    },
    {
        "event_properties.name": "Freelance Dashboard",
        "events": 7,
        "users": 6
    },
    {
        "event_properties.name": "Plant Database",
        "events": 6,
        "users": 6
    },
    {
        "event_properties.name": "PARA and CODER Setup",
        "events": 7,
        "users": 6
    },
    {
        "event_properties.name": "anti_aging_workout_by_bryan_johnson",
        "events": 5,
        "users": 5
    },
    {
        "event_properties.name": "Community Space",
        "events": 5,
        "users": 5
    },
    {
        "event_properties.name": "Simple Tables",
        "events": 5,
        "users": 5
    },
    {
        "event_properties.name": "Customizable Dashboard",
        "events": 5,
        "users": 5
    },
    {
        "event_properties.name": "RPG Repository",
        "events": 5,
        "users": 5
    },
    {
        "event_properties.name": "Meeting Notes Management",
        "events": 4,
        "users": 4
    },
    {
        "event_properties.name": "Advanced Project Management",
        "events": 4,
        "users": 4
    },
    {
        "event_properties.name": "Adventure Hub",
        "events": 4,
        "users": 4
    },
    {
        "event_properties.name": "Plant Tracker",
        "events": 3,
        "users": 3
    },
    {
        "event_properties.name": "Podcast Database",
        "events": 3,
        "users": 3
    },
    {
        "event_properties.name": "Classical Music Database",
        "events": 4,
        "users": 3
    },
    {
        "event_properties.name": "Neighbors Space",
        "events": 3,
        "users": 3
    },
    {
        "event_properties.name": "Coffee Tracker",
        "events": 3,
        "users": 3
    },
    {
        "event_properties.name": "Formula 1",
        "events": 2,
        "users": 2
    },
    {
        "event_properties.name": "Crochet Dashboard",
        "events": 2,
        "users": 2
    },
    {
        "event_properties.name": "AnyType for Content Creators",
        "events": 1,
        "users": 1
    },
    {
        "event_properties.name": "Items Lent out/Borrowed Tracker",
        "events": 1,
        "users": 1
    },
    {
        "event_properties.name": "Animation Database",
        "events": 1,
        "users": 1
    }
]