[
    {
        "event_properties.name": "daily_journal",
        "events": 1080,
        "users": 939
    },
    {
        "event_properties.name": "project_management",
        "events": 664,
        "users": 592
    },
    {
        "event_properties.name": "habit_tracker",
        "events": 590,
        "users": 526
    },
    {
        "event_properties.name": "crm_basic_approach",
        "events": 575,
        "users": 514
    },
    {
        "event_properties.name": "study_hub",
        "events": 543,
        "users": 491
    },
    {
        "event_properties.name": "personal_and_work_pkm",
        "events": 508,
        "users": 444
    },
    {
        "event_properties.name": "team_space",
        "events": 404,
        "users": 362
    },
    {
        "event_properties.name": "family_space",
        "events": 399,
        "users": 362
    },
    {
        "event_properties.name": "zen_system",
        "events": 407,
        "users": 356
    },
    {
        "event_properties.name": "data_vault",
        "events": 381,
        "users": 354
    },
    {
        "event_properties.name": "community_space",
        "events": 375,
        "users": 338
    },
    {
        "event_properties.name": "para_lite",
        "events": 404,
        "users": 337
    },
    {
        "event_properties.name": "anyday",
        "events": 371,
        "users": 320
    },
    {
        "event_properties.name": "para_tasks_resources_meeting_notes_crm",
        "events": 357,
        "users": 317
    },
    {
        "event_properties.name": "movie_database",
        "events": 353,
        "users": 308
    },
    {
        "event_properties.name": "paid_subscriptions_tracking",
        "events": 330,
        "users": 303
    },
    {
        "event_properties.name": "recipe_book_and_meal_planner",
        "events": 321,
        "users": 286
    },
    {
        "event_properties.name": "zettelkasten_smart_notes",
        "events": 319,
        "users": 278
    },
    {
        "event_properties.name": "yapkms_yet_another_pkm_space",
        "events": 288,
        "users": 251
    },
    {
        "event_properties.name": "freelance_dashboard",
        "events": 256,
        "users": 231
    },
    {
        "event_properties.name": "startup_planner",
        "events": 238,
        "users": 217
    },
    {
        "event_properties.name": "unified_space",
        "events": 245,
        "users": 216
    },
    {
        "event_properties.name": "integrated_library",
        "events": 266,
        "users": 209
    },
    {
        "event_properties.name": "trip_planner",
        "events": 213,
        "users": 193
    },
    {
        "event_properties.name": "homepages",
        "events": 189,
        "users": 174
    },
    {
        "event_properties.name": "ultimate_student_os",
        "events": 166,
        "users": 156
    },
    {
        "event_properties.name": "frm_friends_relationship_management",
        "events": 181,
        "users": 155
    },
    {
        "event_properties.name": "space_for_digital_creators",
        "events": 156,
        "users": 144
    },
    {
        "event_properties.name": "para_and_coder_setup",
        "events": 185,
        "users": 141
    },
    {
        "event_properties.name": "anytype_for_content_creators",
        "events": 161,
        "users": 140
    },
    {
        "event_properties.name": "legacy_homepage",
        "events": 129,
        "users": 116
    },
    {
        "event_properties.name": "subscription_tracker",
        "events": 127,
        "users": 112
    },
    {
        "event_properties.name": "a_student_need",
        "events": 119,
        "users": 111
    },
    {
        "event_properties.name": "language_flashcards",
        "events": 121,
        "users": 109
    },
    {
        "event_properties.name": "advanced_project_management",
        "events": 116,
        "users": 106
    },
    {
        "event_properties.name": "routine_set_ticker",
        "events": 113,
        "users": 103
    },
    {
        "event_properties.name": "plant_database",
        "events": 103,
        "users": 93
    },
    {
        "event_properties.name": "customizable_dashboard",
        "events": 87,
        "users": 80
    },
    {
        "event_properties.name": "journal_diary",
        "events": 85,
        "users": 79
    },
    {
        "event_properties.name": "meeting_notes_management",
        "events": 88,
        "users": 79
    },
    {
        "event_properties.name": "neighbors_space",
        "events": 75,
        "users": 69
    },
    {
        "event_properties.name": "create_your_own_world",
        "events": 68,
        "users": 63
    },
    {
        "event_properties.name": "rpg_repository",
        "events": 73,
        "users": 63
    },
    {
        "event_properties.name": "Daily Journal",
        "events": 65,
        "users": 61
    },
    {
        "event_properties.name": "Personal and Work PKM",
        "events": 60,
        "users": 56
    },
    {
        "event_properties.name": "story_forge_project_manager",
        "events": 58,
        "users": 54
    },
    {
        "event_properties.name": "anti_aging_workout_by_bryan_johnson",
        "events": 45,
        "users": 43
    },
    {
        "event_properties.name": "podcast_database",
        "events": 45,
        "users": 42
    },
    {
        "event_properties.name": "simple_tables",
        "events": 41,
        "users": 39
    },
    {
        "event_properties.name": "Project Management",
        "events": 43,
        "users": 36
    },
    {
        "event_properties.name": "Family Space",
        "events": 43,
        "users": 36
    },
    {
        "event_properties.name": "PARA - Lite",
        "events": 41,
        "users": 36
    },
    {
        "event_properties.name": "gaming_hud",
        "events": 38,
        "users": 34
    },
    {
        "event_properties.name": "animation_database",
        "events": 34,
        "users": 32
    },
    {
        "event_properties.name": "Habit Tracker",
        "events": 33,
        "users": 28
    },
    {
        "event_properties.name": "Trip Planner",
        "events": 35,
        "users": 28
    },
    {
        "event_properties.name": "Fully integrated Experience",
        "events": 31,
        "users": 26
    },
    {
        "event_properties.name": "Recipe Book and Meal Planner",
        "events": 27,
        "users": 25
    },
    {
        "event_properties.name": "classical_music_database",
        "events": 28,
        "users": 25
    },
    {
        "event_properties.name": "Zen System",
        "events": 27,
        "users": 24
    },
    {
        "event_properties.name": "formula_1",
        "events": 24,
        "users": 24
    },
    {
        "event_properties.name": "plant_tracker",
        "events": 21,
        "users": 21
    },
    {
        "event_properties.name": "coffee_tracker",
        "events": 27,
        "users": 21
    },
    {
        "event_properties.name": "Team Space",
        "events": 23,
        "users": 19
    },
    {
        "event_properties.name": "YAPKMS - Yet Another PKM Space",
        "events": 19,
        "users": 18
    },
    {
        "event_properties.name": "Zettelkasten: Smart Notes",
        "events": 20,
        "users": 17
    },
    {
        "event_properties.name": "Movie Database",
        "events": 17,
        "users": 17
    },
    {
        "event_properties.name": "Paid Subscriptions Tracking",
        "events": 19,
        "users": 17
    },
    {
        "event_properties.name": "Study Hub",
        "events": 17,
        "users": 17
    },
    {
        "event_properties.name": "crochet_dashboard",
        "events": 15,
        "users": 15
    },
    {
        "event_properties.name": "Unified Space",
        "events": 16,
        "users": 14
    },
    {
        "event_properties.name": "AnyDay",
        "events": 14,
        "users": 13
    },
    {
        "event_properties.name": "adventure_hub",
        "events": 13,
        "users": 13
    },
    {
        "event_properties.name": "Subscription Tracker",
        "events": 14,
        "users": 12
    },
    {
        "event_properties.name": "CRM: Basic Approach",
        "events": 11,
        "users": 11
    },
    {
        "event_properties.name": "Homepages",
        "events": 14,
        "users": 11
    },
    {
        "event_properties.name": "Data Vault",
        "events": 11,
        "users": 11
    },
    {
        "event_properties.name": "PARA and CODER Setup",
        "events": 13,
        "users": 11
    },
    {
        "event_properties.name": "Startup Planner",
        "events": 13,
        "users": 11
    },
    {
        "event_properties.name": "items_lent_out_borrowed_tracker",
        "events": 13,
        "users": 11
    },
    {
        "event_properties.name": "Advanced Project Management",
        "events": 9,
        "users": 9
    },
    {
        "event_properties.name": "Community Space",
        "events": 8,
        "users": 8
    },
    {
        "event_properties.name": "Integrated Library",
        "events": 9,
        "users": 8
    },
    {
        "event_properties.name": "Ultimate Student OS",
        "events": 8,
        "users": 8
    },
    {
        "event_properties.name": "Meeting Notes Management",
        "events": 8,
        "users": 7
    },
    {
        "event_properties.name": "Routine Set Ticker",
        "events": 7,
        "users": 7
    },
    {
        "event_properties.name": "Journal & Diary",
        "events": 9,
        "users": 7
    },
    {
        "event_properties.name": "FRM: Friends Relationship Management",
        "events": 7,
        "users": 7
    },
    {
        "event_properties.name": "Space for Digital Creators",
        "events": 7,
        "users": 7
    },
    {
        "event_properties.name": "Customizable Dashboard",
        "events": 11,
        "users": 7
    },
    {
        "event_properties.name": "Language Flashcards",
        "events": 7,
        "users": 6
    },
    {
        "event_properties.name": "Crochet Dashboard",
        "events": 8,
        "users": 6
    },
    {
        "event_properties.name": "Simple Tables",
        "events": 6,
        "users": 6
    },
    {
        "event_properties.name": "Story Forge Project Manager",
        "events": 6,
        "users": 5
    },
    {
        "event_properties.name": "Plant Tracker",
        "events": 5,
        "users": 5
    },
    {
        "event_properties.name": "Plant Database",
        "events": 5,
        "users": 5
    },
    {
        "event_properties.name": "A Student Need",
        "events": 4,
        "users": 4
    },
    {
        "event_properties.name": "Freelance Dashboard",
        "events": 4,
        "users": 4
    },
    {
        "event_properties.name": "Podcast Database",
        "events": 4,
        "users": 4
    },
    {
        "event_properties.name": "Focus Matrix-All In One Page",
        "events": 5,
        "users": 4
    },
    {
        "event_properties.name": "Neighbors Space",
        "events": 5,
        "users": 4
    },
    {
        "event_properties.name": "Legacy Homepage",
        "events": 6,
        "users": 4
    },
    {
        "event_properties.name": "Formula 1",
        "events": 4,
        "users": 4
    },
    {
        "event_properties.name": "Gaming Hud",
        "events": 3,
        "users": 3
    },
    {
        "event_properties.name": "Anti-Aging Workout by Bryan Johnson",
        "events": 3,
        "users": 3
    },
    {
        "event_properties.name": "Create Your Own World",
        "events": 4,
        "users": 3
    },
    {
        "event_properties.name": "AnyType for Content Creators",
        "events": 2,
        "users": 2
    },
    {
        "event_properties.name": "Space for Student",
        "events": 2,
        "users": 2
    },
    {
        "event_properties.name": "Solution log",
        "events": 2,
        "users": 2
    },
    {
        "event_properties.name": "Animation Database",
        "events": 1,
        "users": 1
    },
    {
        "event_properties.name": "Adventure Hub",
        "events": 1,
        "users": 1
    },
    {
        "event_properties.name": "Coffee Tracker",
        "events": 1,
        "users": 1
    }
]