{
  "sbType": "SubObject",
  "snapshot": {
    "data": {
      "blocks": [
        {
          "id": "ot-relationOption",
          "fields": {
            "analyticsOriginalId": "ot-relationOption"
          },
          "restrictions": {},
          "childrenIds": [
            "header",
            "templates",
            "dataview"
          ]
        },
        {
          "id": "header",
          "restrictions": {
            "edit": true,
            "remove": true,
            "drag": true,
            "dropOn": true
          },
          "childrenIds": [
            "title",
            "description",
            "featuredRelations"
          ],
          "layout": {
            "style": "Header"
          }
        },
        {
          "id": "templates",
          "fields": {
            "_defaultRecordFields": {
              "targetObjectType": "ot-relationOption"
            }
          },
          "dataview": {
            "source": [
              "ot-template"
            ],
            "views": [
              {
                "id": "_view2_1",
                "name": "All",
                "sorts": [
                  {
                    "RelationKey": "name"
                  }
                ],
                "filters": [
                  {
                    "RelationKey": "targetObjectType",
                    "condition": "Equal",
                    "value": "ot-relationOption"
                  }
                ]
              }
            ]
          }
        },
        {
          "id": "dataview",
          "dataview": {
            "source": [
              "ot-relationOption"
            ],
            "views": [
              {
                "id": "_view1_1",
                "name": "All",
                "sorts": [
                  {
                    "RelationKey": "name"
                  }
                ]
              }
            ]
          }
        },
        {
          "id": "title",
          "fields": {
            "_detailsKey": [
              "name",
              "done"
            ]
          },
          "restrictions": {
            "remove": true,
            "drag": true,
            "dropOn": true
          },
          "text": {
            "style": "Title",
            "marks": {}
          }
        },
        {
          "id": "description",
          "fields": {
            "_detailsKey": "description"
          },
          "restrictions": {
            "remove": true,
            "drag": true,
            "dropOn": true
          },
          "text": {
            "style": "Description",
            "marks": {}
          }
        },
        {
          "id": "featuredRelations",
          "restrictions": {
            "remove": true,
            "drag": true,
            "dropOn": true
          },
          "featuredRelations": {}
        }
      ],
      "details": {
        "creator": "_anytype_profile",
        "description": "Object that contains a relation option",
        "featuredRelations": [
          "description",
          "type",
          "sourceObject"
        ],
        "iconEmoji": "🥚",
        "id": "ot-relationOption",
        "isHidden": true,
        "lastChangeId": "",
        "lastModifiedBy": "_anytype_profile",
        "layout": 4,
        "links": [],
        "name": "Relation option",
        "recommendedLayout": 13,
        "recommendedRelations": [],
        "restrictions": [
          3,
          6,
          5,
          7,
          4,
          1
        ],
        "smartblockTypes": [
          513
        ],
        "snippet": "",
        "type": "ot-objectType"
      },
      "objectTypes": [
        "ot-objectType"
      ],
      "relationLinks": [
        {
          "key": "id",
          "format": "object"
        },
        {
          "key": "snippet"
        },
        {
          "key": "description"
        },
        {
          "key": "iconEmoji",
          "format": "emoji"
        },
        {
          "key": "name",
          "format": "shorttext"
        },
        {
          "key": "recommendedRelations",
          "format": "object"
        },
        {
          "key": "createdDate",
          "format": "date"
        },
        {
          "key": "layout",
          "format": "number"
        },
        {
          "key": "isHidden",
          "format": "checkbox"
        },
        {
          "key": "recommendedLayout",
          "format": "number"
        },
        {
          "key": "type",
          "format": "object"
        },
        {
          "key": "smartblockTypes",
          "format": "number"
        },
        {
          "key": "sourceObject",
          "format": "object"
        },
        {
          "key": "creator",
          "format": "object"
        },
        {
          "key": "lastModifiedDate",
          "format": "date"
        },
        {
          "key": "lastOpenedDate",
          "format": "date"
        },
        {
          "key": "lastModifiedBy",
          "format": "object"
        },
        {
          "key": "featuredRelations",
          "format": "object"
        },
        {
          "key": "workspaceId",
          "format": "object"
        },
        {
          "key": "iconImage",
          "format": "file"
        },
        {
          "key": "layoutAlign",
          "format": "number"
        },
        {
          "key": "coverId"
        },
        {
          "key": "coverScale",
          "format": "number"
        },
        {
          "key": "coverType",
          "format": "number"
        },
        {
          "key": "coverX",
          "format": "number"
        },
        {
          "key": "coverY",
          "format": "number"
        },
        {
          "key": "isFavorite",
          "format": "checkbox"
        },
        {
          "key": "links",
          "format": "object"
        },
        {
          "key": "internalFlags",
          "format": "number"
        },
        {
          "key": "restrictions",
          "format": "number"
        }
      ]
    }
  }
}
